docusign_click/__init__.py
docusign_click/apis/__init__.py
docusign_click/apis/accounts_api.py
docusign_click/client/__init__.py
docusign_click/client/api_client.py
docusign_click/client/api_exception.py
docusign_click/client/api_response.py
docusign_click/client/configuration.py
docusign_click/client/auth/__init__.py
docusign_click/client/auth/oauth.py
docusign_click/models/__init__.py
docusign_click/models/agree_button_styles.py
docusign_click/models/agreement_statement_styles.py
docusign_click/models/base_agree_button_styles.py
docusign_click/models/bulk_clickwrap_request.py
docusign_click/models/clickwrap_agreements_response.py
docusign_click/models/clickwrap_delete_response.py
docusign_click/models/clickwrap_request.py
docusign_click/models/clickwrap_response.py
docusign_click/models/clickwrap_scheduled_reacceptance.py
docusign_click/models/clickwrap_summary_response.py
docusign_click/models/clickwrap_transfer_request.py
docusign_click/models/clickwrap_version.py
docusign_click/models/clickwrap_version_delete_info.py
docusign_click/models/clickwrap_version_delete_response.py
docusign_click/models/clickwrap_version_response.py
docusign_click/models/clickwrap_version_summary_response.py
docusign_click/models/clickwrap_versions_delete_response.py
docusign_click/models/clickwrap_versions_paged_response.py
docusign_click/models/clickwrap_versions_response.py
docusign_click/models/clickwraps_delete_response.py
docusign_click/models/clickwraps_response.py
docusign_click/models/container_styles.py
docusign_click/models/conversion_document.py
docusign_click/models/data_field.py
docusign_click/models/disclosure_link_styles.py
docusign_click/models/display_settings.py
docusign_click/models/document.py
docusign_click/models/document_conversion_request.py
docusign_click/models/document_conversion_response.py
docusign_click/models/document_data.py
docusign_click/models/document_link_styles.py
docusign_click/models/document_link_styles_focus.py
docusign_click-1.4.0.dist-info/LICENSE
docusign_click-1.4.0.dist-info/METADATA
docusign_click-1.4.0.dist-info/WHEEL
docusign_click-1.4.0.dist-info/top_level.txt
docusign_click-1.4.0.dist-info/RECORD
