Metadata-Version: 2.1
Name: docusign-click
Version: 1.4.0
Summary: DocuSign Click API
Home-page: 
Author-email: devcenter@docusign.com
Keywords: Swagger,DocuSign Click API
License-File: LICENSE
